app/__init__.py
app/main.py
app/config/__init__.py
app/config/default.ini
app/core/__init__.py
app/core/package_class.py
block_licenses-0.0.10.dist-info/LICENSE
block_licenses-0.0.10.dist-info/METADATA
block_licenses-0.0.10.dist-info/WHEEL
block_licenses-0.0.10.dist-info/entry_points.txt
block_licenses-0.0.10.dist-info/top_level.txt
block_licenses-0.0.10.dist-info/RECORD
