Metadata-Version: 2.1
Name: block-licenses
Version: 0.0.10
Summary: CLI tool that helps us easily define which licenses are not good based on the requirements.txt file.         It uses pkg_resources to get details from the packages, given us the licenses listed byt the package owner and         returns exit 1 if found a package that contains a blocked license.
Home-page: https://github.com/MarcelFox/block-licenses
Author: Marcel Fox
Author-email: marcelfox@live.com
License: MIT
License-File: LICENSE
Requires-Dist: Click
